{
  "$id": "1",
  "definitionId": "3a0b7db5-3307-b6a2-a35a-6cca70319324",
  "versionId": "3a0b7dc2-d98d-23f5-69fa-532f5ca4adc1",
  "name": "Office Equipment Request",
  "displayName": "Office Equipment Request",
  "version": 1,
  "variables": {
    "$id": "2",
    "data": {}
  },
  "customAttributes": {
    "$id": "3",
    "data": {}
  },
  "isSingleton": false,
  "persistenceBehavior": "WorkflowBurst",
  "deleteCompletedInstances": false,
  "isPublished": true,
  "isLatest": true,
  "createdAt": "2023-05-30T07:36:12.941066Z",
  "activities": [
    {
      "$id": "4",
      "activityId": "8a18ca7a-2219-4906-b51f-0c0b101fc990",
      "type": "Fork",
      "displayName": "Branch Manager makes decision",
      "persistWorkflow": false,
      "loadWorkflowContext": false,
      "saveWorkflowContext": false,
      "properties": [
        {
          "$id": "5",
          "name": "Branches",
          "expressions": {
            "$id": "6",
            "Json": "[\"Approve\",\"Reject\"]"
          }
        }
      ],
      "propertyStorageProviders": {}
    },
    {
      "$id": "7",
      "activityId": "aa680588-fc5d-4497-b0a2-52aedec55bfe",
      "type": "SignalReceived",
      "displayName": "Rejected",
      "persistWorkflow": false,
      "loadWorkflowContext": false,
      "saveWorkflowContext": false,
      "properties": [
        {
          "$id": "8",
          "name": "Signal",
          "syntax": "JavaScript",
          "expressions": {
            "$id": "9",
            "Literal": "",
            "JavaScript": "workflowSignals.HoORejected"
          }
        }
      ],
      "propertyStorageProviders": {}
    },
    {
      "$id": "10",
      "activityId": "dca91e19-fa3f-43b8-8614-994388629feb",
      "type": "SendEmailToInstanceCreatorAndOther",
      "displayName": "Send notification to staff: Request was rejected",
      "persistWorkflow": false,
      "loadWorkflowContext": false,
      "saveWorkflowContext": false,
      "properties": [
        {
          "$id": "11",
          "name": "To",
          "expressions": {
            "$id": "12"
          }
        },
        {
          "$id": "13",
          "name": "Subject",
          "syntax": "JavaScript",
          "expressions": {
            "$id": "14",
            "JavaScript": "const userInfo = getRequestUser();\r\nreturn `[Office Equipment Request] Rejected - [${userInfo.Project}] - ${userInfo.Name}`;"
          }
        },
        {
          "$id": "15",
          "name": "Attachments",
          "expressions": {
            "$id": "16"
          }
        },
        {
          "$id": "17",
          "name": "Body",
          "syntax": "JavaScript",
          "expressions": {
            "$id": "18",
            "JavaScript": "const emailTemplate = getVariable('EmailTemplate');\r\nreturn `\r\n<p>Yêu cầu cấp thiết bị cho văn phòng đã bị từ chối.</p>\r\n<p>Lý do: ${activityExecutionContext.Input.Reason}</p>\r\n<p>Từ chối bởi: ${activityExecutionContext.Input.TriggeredBy}</p>\r\n<blockquote>\r\n${emailTemplate}\r\n</blockquote>\r\n`"
          }
        }
      ],
      "propertyStorageProviders": {}
    },
    {
      "$id": "19",
      "activityId": "0784837d-0af6-4fb9-99bb-73e294c0979b",
      "type": "Finish",
      "displayName": "Request was rejected",
      "persistWorkflow": false,
      "loadWorkflowContext": false,
      "saveWorkflowContext": false,
      "properties": [
        {
          "$id": "20",
          "name": "ActivityOutput",
          "expressions": {
            "$id": "21",
            "Literal": "Rejected"
          }
        },
        {
          "$id": "22",
          "name": "OutcomeNames",
          "expressions": {
            "$id": "23"
          }
        }
      ],
      "propertyStorageProviders": {}
    },
    {
      "$id": "24",
      "activityId": "2409b0d2-71c6-479d-bd5b-e4c0e8c7ca24",
      "type": "SignalReceived",
      "displayName": "Approved",
      "persistWorkflow": false,
      "loadWorkflowContext": false,
      "saveWorkflowContext": false,
      "properties": [
        {
          "$id": "25",
          "name": "Signal",
          "syntax": "JavaScript",
          "expressions": {
            "$id": "26",
            "JavaScript": "workflowSignals.HoOApproved",
            "Literal": ""
          }
        }
      ],
      "propertyStorageProviders": {}
    },
    {
      "$id": "27",
      "activityId": "9e026df5-a95a-4850-8d87-fdca59aaa063",
      "type": "CustomEmail",
      "displayName": "Send email to IT",
      "persistWorkflow": false,
      "loadWorkflowContext": false,
      "saveWorkflowContext": false,
      "properties": [
        {
          "$id": "28",
          "name": "To",
          "expressions": {
            "$id": "29",
            "Json": "[\"it@ncc.asia\"]"
          }
        },
        {
          "$id": "30",
          "name": "Subject",
          "syntax": "JavaScript",
          "expressions": {
            "$id": "31",
            "JavaScript": "const userInfo = getRequestUser();\r\nreturn `[Office Equipment Request] [${userInfo.Project}] - ${userInfo.Name}`;",
            "Literal": ""
          }
        },
        {
          "$id": "32",
          "name": "Attachments",
          "expressions": {
            "$id": "33"
          }
        },
        {
          "$id": "34",
          "name": "Body",
          "syntax": "JavaScript",
          "expressions": {
            "$id": "35",
            "Literal": "",
            "JavaScript": "const rejectSignalUrl = getCustomSignalUrlWithForm(workflowSignals.Rejected, [signalInputTypes.Reason, signalInputTypes.TriggeredBy]);\r\nconst userInfo = getRequestUser();\r\nconst emailTemplate = getVariable('EmailTemplate');\r\nreturn `\r\n<p>Người gửi: ${userInfo.Name} (${userInfo.Email})</p>\r\n<p>Nội dung:</p>\r\n<div>\r\n${emailTemplate}\r\n</div>\r\n<div>\r\n<a href=\"${getCustomSignalUrl(workflowSignals.Approved)}\" style=\"margin-right:10px;\">Duyệt</a>&nbsp;&nbsp;&nbsp;&nbsp;&nbsp;&nbsp;&nbsp;&nbsp;\r\n<a href=\"${rejectSignalUrl}\" style=\"margin-right:10px;\">Từ chối</a>\r\n</div>\r\n`;"
          }
        },
        {
          "$id": "36",
          "name": "Cc",
          "expressions": {
            "$id": "37"
          }
        },
        {
          "$id": "38",
          "name": "Bcc",
          "expressions": {
            "$id": "39"
          }
        }
      ],
      "propertyStorageProviders": {}
    },
    {
      "$id": "40",
      "activityId": "1fc7a33d-437f-47ed-9a95-2bead5da51ff",
      "type": "Fork",
      "displayName": "IT reviews",
      "persistWorkflow": false,
      "loadWorkflowContext": false,
      "saveWorkflowContext": false,
      "properties": [
        {
          "$id": "41",
          "name": "Branches",
          "expressions": {
            "$id": "42",
            "Json": "[\"Approve\",\"Reject\"]"
          }
        }
      ],
      "propertyStorageProviders": {}
    },
    {
      "$id": "43",
      "activityId": "e64a738c-f168-4332-a022-f7bb2ec1003a",
      "type": "SendEmailToInstanceCreatorAndOther",
      "displayName": "Send notification to staff: Request was approved",
      "persistWorkflow": false,
      "loadWorkflowContext": false,
      "saveWorkflowContext": false,
      "properties": [
        {
          "$id": "44",
          "name": "To",
          "expressions": {
            "$id": "45"
          }
        },
        {
          "$id": "46",
          "name": "Subject",
          "syntax": "JavaScript",
          "expressions": {
            "$id": "47",
            "JavaScript": "const userInfo = getRequestUser();\r\nreturn `[Office Equiqment Request] Approved - [${userInfo.Project}] - ${userInfo.Name}`",
            "Literal": ""
          }
        },
        {
          "$id": "48",
          "name": "Attachments",
          "expressions": {
            "$id": "49"
          }
        },
        {
          "$id": "50",
          "name": "Body",
          "syntax": "JavaScript",
          "expressions": {
            "$id": "51",
            "JavaScript": "const emailTemplate = getVariable('EmailTemplate');\r\nreturn `\r\n<p>Yêu cầu cấp thiết bị văn phòng đã được duyệt</p>\r\n<blockquote>\r\n${emailTemplate}\r\n</blockquote>\r\n`",
            "Literal": ""
          }
        }
      ],
      "propertyStorageProviders": {}
    },
    {
      "$id": "52",
      "activityId": "d8534a49-0976-4e87-be2d-8b50c2b179e9",
      "type": "SignalReceived",
      "displayName": "Approved",
      "persistWorkflow": false,
      "loadWorkflowContext": false,
      "saveWorkflowContext": false,
      "properties": [
        {
          "$id": "53",
          "name": "Signal",
          "syntax": "JavaScript",
          "expressions": {
            "$id": "54",
            "JavaScript": "workflowSignals.Approved"
          }
        }
      ],
      "propertyStorageProviders": {}
    },
    {
      "$id": "55",
      "activityId": "838ce456-e857-4050-ae5f-fa42553f5c97",
      "type": "SignalReceived",
      "displayName": "Rejected",
      "persistWorkflow": false,
      "loadWorkflowContext": false,
      "saveWorkflowContext": false,
      "properties": [
        {
          "$id": "56",
          "name": "Signal",
          "syntax": "JavaScript",
          "expressions": {
            "$id": "57",
            "JavaScript": "workflowSignals.Rejected"
          }
        }
      ],
      "propertyStorageProviders": {}
    },
    {
      "$id": "58",
      "activityId": "ee12c48c-5484-4117-b1c3-56bf5fa1df40",
      "type": "SendEmailToInstanceCreatorAndOther",
      "displayName": "Send notification to staff: Request was rejected",
      "persistWorkflow": false,
      "loadWorkflowContext": false,
      "saveWorkflowContext": false,
      "properties": [
        {
          "$id": "59",
          "name": "To",
          "expressions": {
            "$id": "60"
          }
        },
        {
          "$id": "61",
          "name": "Subject",
          "syntax": "JavaScript",
          "expressions": {
            "$id": "62",
            "JavaScript": "const userInfo = getRequestUser();\r\n`[Office Equipment Request] Rejected - [${userInfo.Project}] - ${userInfo.Name}`"
          }
        },
        {
          "$id": "63",
          "name": "Attachments",
          "expressions": {
            "$id": "64"
          }
        },
        {
          "$id": "65",
          "name": "Body",
          "syntax": "JavaScript",
          "expressions": {
            "$id": "66",
            "Literal": "",
            "JavaScript": "const emailTemplate = getVariable('EmailTemplate');\r\nreturn `\r\n<p>Yêu cầu cấp thiết bị văn phòng đã bị từ chối.</p>\r\n<p>Lý do: ${activityExecutionContext.Input.Reason}</p>\r\n<p>Từ chối bởi: ${activityExecutionContext.Input.TriggeredBy}</p>\r\n<blockquote>\r\n${emailTemplate}\r\n</blockquote>\r\n`"
          }
        }
      ],
      "propertyStorageProviders": {}
    },
    {
      "$id": "67",
      "activityId": "3ca995eb-2fcb-4bac-b188-3c7e791c7ec1",
      "type": "Finish",
      "displayName": "Request was approved",
      "persistWorkflow": false,
      "loadWorkflowContext": false,
      "saveWorkflowContext": false,
      "properties": [
        {
          "$id": "68",
          "name": "ActivityOutput",
          "expressions": {
            "$id": "69",
            "Literal": "Approved"
          }
        },
        {
          "$id": "70",
          "name": "OutcomeNames",
          "expressions": {
            "$id": "71"
          }
        }
      ],
      "propertyStorageProviders": {}
    },
    {
      "$id": "72",
      "activityId": "3ab37c38-fc56-4d2c-a597-39cf6446ce12",
      "type": "Finish",
      "displayName": "Request was rejected",
      "persistWorkflow": false,
      "loadWorkflowContext": false,
      "saveWorkflowContext": false,
      "properties": [
        {
          "$id": "73",
          "name": "ActivityOutput",
          "expressions": {
            "$id": "74",
            "Literal": "Rejected"
          }
        },
        {
          "$id": "75",
          "name": "OutcomeNames",
          "expressions": {
            "$id": "76"
          }
        }
      ],
      "propertyStorageProviders": {}
    },
    {
      "$id": "77",
      "activityId": "98a78226-e450-4383-a5cb-5fafa6b4c354",
      "type": "HttpEndpoint",
      "displayName": "Trigger Workflow",
      "persistWorkflow": false,
      "loadWorkflowContext": false,
      "saveWorkflowContext": false,
      "properties": [
        {
          "$id": "78",
          "name": "Path",
          "expressions": {
            "$id": "79",
            "Literal": "equipment-request"
          }
        },
        {
          "$id": "80",
          "name": "Methods",
          "expressions": {
            "$id": "81",
            "Json": "[\"POST\"]"
          }
        },
        {
          "$id": "82",
          "name": "ReadContent",
          "expressions": {
            "$id": "83"
          }
        },
        {
          "$id": "84",
          "name": "TargetType",
          "expressions": {
            "$id": "85"
          }
        },
        {
          "$id": "86",
          "name": "Schema",
          "syntax": "Literal",
          "expressions": {
            "$id": "87",
            "Literal": ""
          }
        },
        {
          "$id": "88",
          "name": "Authorize",
          "expressions": {
            "$id": "89"
          }
        },
        {
          "$id": "90",
          "name": "Policy",
          "expressions": {
            "$id": "91"
          }
        }
      ],
      "propertyStorageProviders": {}
    },
    {
      "$id": "92",
      "activityId": "b9078a5b-8b54-4f22-bfc0-c75fc0f62dfa",
      "type": "SetVariable",
      "displayName": "Set Variable Request",
      "persistWorkflow": false,
      "loadWorkflowContext": false,
      "saveWorkflowContext": false,
      "properties": [
        {
          "$id": "93",
          "name": "VariableName",
          "expressions": {
            "$id": "94",
            "Literal": "Request"
          }
        },
        {
          "$id": "95",
          "name": "Value",
          "syntax": "JavaScript",
          "expressions": {
            "$id": "96",
            "Literal": "",
            "JavaScript": "input.Body"
          }
        }
      ],
      "propertyStorageProviders": {}
    },
    {
      "$id": "97",
      "activityId": "018d2656-1ef4-4f96-9236-2f4739c02506",
      "type": "SetRequestUserVariable",
      "displayName": "Set RequestUser Variable",
      "persistWorkflow": false,
      "loadWorkflowContext": false,
      "saveWorkflowContext": false,
      "properties": [],
      "propertyStorageProviders": {}
    },
    {
      "$id": "98",
      "activityId": "735f2071-f6ef-4351-9f48-844aac9b2e0d",
      "type": "SetVariable",
      "displayName": "Set Email Template Variable",
      "persistWorkflow": false,
      "loadWorkflowContext": false,
      "saveWorkflowContext": false,
      "properties": [
        {
          "$id": "99",
          "name": "VariableName",
          "expressions": {
            "$id": "100",
            "Literal": "EmailTemplate"
          }
        },
        {
          "$id": "101",
          "name": "Value",
          "syntax": "JavaScript",
          "expressions": {
            "$id": "102",
            "JavaScript": "const requestInfo = getVariable('Request');\r\nconst officeInfo = getOfficeInfo(requestInfo.CurrentOffice);\r\nreturn `\r\n<p>Văn phòng đang làm việc: ${officeInfo.DisplayName}</p>\r\n<p>Thiết bị cần request: ${requestInfo.Equipment}</p>\r\n<p>Lý do: ${requestInfo.Reason}</p>\r\n`"
          }
        }
      ],
      "propertyStorageProviders": {}
    },
    {
      "$id": "103",
      "activityId": "425ef51b-13b6-4481-aa58-1f76ddb28dc8",
      "type": "CustomEmail",
      "displayName": "Send email to branch manager",
      "persistWorkflow": false,
      "loadWorkflowContext": false,
      "saveWorkflowContext": false,
      "properties": [
        {
          "$id": "104",
          "name": "To",
          "syntax": "JavaScript",
          "expressions": {
            "$id": "105",
            "JavaScript": "const requestInfo = getVariable('Request');\r\nconst officeInfo = getOfficeInfo(requestInfo.CurrentOffice);\r\n\r\nreturn [officeInfo.HeadOfOfficeEmail];"
          }
        },
        {
          "$id": "106",
          "name": "Subject",
          "syntax": "JavaScript",
          "expressions": {
            "$id": "107",
            "JavaScript": "const userInfo = getRequestUser();\r\n`[Office Equipment Request] [${userInfo.Project}] - ${userInfo.Name}`"
          }
        },
        {
          "$id": "108",
          "name": "Attachments",
          "expressions": {
            "$id": "109"
          }
        },
        {
          "$id": "110",
          "name": "Body",
          "syntax": "JavaScript",
          "expressions": {
            "$id": "111",
            "JavaScript": "const rejectSignalUrl = getCustomSignalUrlWithForm(workflowSignals.HoORejected, [signalInputTypes.Reason, signalInputTypes.TriggeredBy]);\r\nconst emailTemplate = getVariable(\"EmailTemplate\");\r\nreturn `\r\n<p>Người gửi: ${currentUser.Name} (${currentUser.Email})</p>\r\n<p>Nội dung:</p>\r\n<div>\r\n${emailTemplate}\r\n</div>\r\n<div>\r\n<a href=\"${getCustomSignalUrl(workflowSignals.HoOApproved)}\" style=\"margin-right:10px;\">Duyệt</a>&nbsp;&nbsp;&nbsp;&nbsp;&nbsp;&nbsp;&nbsp;&nbsp;\r\n<a href=\"${rejectSignalUrl}\" style=\"margin-right:10px;\">Từ chối</a>&nbsp;&nbsp;&nbsp;&nbsp;&nbsp;&nbsp;&nbsp;&nbsp;\r\n</div>\r\n`;"
          }
        },
        {
          "$id": "112",
          "name": "Cc",
          "expressions": {
            "$id": "113"
          }
        },
        {
          "$id": "114",
          "name": "Bcc",
          "expressions": {
            "$id": "115"
          }
        }
      ],
      "propertyStorageProviders": {}
    }
  ],
  "connections": [
    {
      "$id": "116",
      "sourceActivityId": "8a18ca7a-2219-4906-b51f-0c0b101fc990",
      "targetActivityId": "aa680588-fc5d-4497-b0a2-52aedec55bfe",
      "outcome": "Reject"
    },
    {
      "$id": "117",
      "sourceActivityId": "aa680588-fc5d-4497-b0a2-52aedec55bfe",
      "targetActivityId": "dca91e19-fa3f-43b8-8614-994388629feb",
      "outcome": "Done"
    },
    {
      "$id": "118",
      "sourceActivityId": "dca91e19-fa3f-43b8-8614-994388629feb",
      "targetActivityId": "0784837d-0af6-4fb9-99bb-73e294c0979b",
      "outcome": "Done"
    },
    {
      "$id": "119",
      "sourceActivityId": "8a18ca7a-2219-4906-b51f-0c0b101fc990",
      "targetActivityId": "2409b0d2-71c6-479d-bd5b-e4c0e8c7ca24",
      "outcome": "Approve"
    },
    {
      "$id": "120",
      "sourceActivityId": "2409b0d2-71c6-479d-bd5b-e4c0e8c7ca24",
      "targetActivityId": "9e026df5-a95a-4850-8d87-fdca59aaa063",
      "outcome": "Done"
    },
    {
      "$id": "121",
      "sourceActivityId": "9e026df5-a95a-4850-8d87-fdca59aaa063",
      "targetActivityId": "1fc7a33d-437f-47ed-9a95-2bead5da51ff",
      "outcome": "Done"
    },
    {
      "$id": "122",
      "sourceActivityId": "1fc7a33d-437f-47ed-9a95-2bead5da51ff",
      "targetActivityId": "d8534a49-0976-4e87-be2d-8b50c2b179e9",
      "outcome": "Approve"
    },
    {
      "$id": "123",
      "sourceActivityId": "d8534a49-0976-4e87-be2d-8b50c2b179e9",
      "targetActivityId": "e64a738c-f168-4332-a022-f7bb2ec1003a",
      "outcome": "Done"
    },
    {
      "$id": "124",
      "sourceActivityId": "1fc7a33d-437f-47ed-9a95-2bead5da51ff",
      "targetActivityId": "838ce456-e857-4050-ae5f-fa42553f5c97",
      "outcome": "Reject"
    },
    {
      "$id": "125",
      "sourceActivityId": "838ce456-e857-4050-ae5f-fa42553f5c97",
      "targetActivityId": "ee12c48c-5484-4117-b1c3-56bf5fa1df40",
      "outcome": "Done"
    },
    {
      "$id": "126",
      "sourceActivityId": "e64a738c-f168-4332-a022-f7bb2ec1003a",
      "targetActivityId": "3ca995eb-2fcb-4bac-b188-3c7e791c7ec1",
      "outcome": "Done"
    },
    {
      "$id": "127",
      "sourceActivityId": "ee12c48c-5484-4117-b1c3-56bf5fa1df40",
      "targetActivityId": "3ab37c38-fc56-4d2c-a597-39cf6446ce12",
      "outcome": "Done"
    },
    {
      "$id": "128",
      "sourceActivityId": "98a78226-e450-4383-a5cb-5fafa6b4c354",
      "targetActivityId": "b9078a5b-8b54-4f22-bfc0-c75fc0f62dfa",
      "outcome": "Done"
    },
    {
      "$id": "129",
      "sourceActivityId": "b9078a5b-8b54-4f22-bfc0-c75fc0f62dfa",
      "targetActivityId": "735f2071-f6ef-4351-9f48-844aac9b2e0d",
      "outcome": "Done"
    },
    {
      "$id": "130",
      "sourceActivityId": "735f2071-f6ef-4351-9f48-844aac9b2e0d",
      "targetActivityId": "018d2656-1ef4-4f96-9236-2f4739c02506",
      "outcome": "Done"
    },
    {
      "$id": "131",
      "sourceActivityId": "018d2656-1ef4-4f96-9236-2f4739c02506",
      "targetActivityId": "425ef51b-13b6-4481-aa58-1f76ddb28dc8",
      "outcome": "Done"
    },
    {
      "$id": "132",
      "sourceActivityId": "425ef51b-13b6-4481-aa58-1f76ddb28dc8",
      "targetActivityId": "8a18ca7a-2219-4906-b51f-0c0b101fc990",
      "outcome": "Done"
    }
  ],
  "id": "3a0b7dc2-d98d-23f5-69fa-532f5ca4adc1"
}